quantinuum_schemas/__init__.py
quantinuum_schemas/exceptions.py
quantinuum_schemas/py.typed
quantinuum_schemas/models/__init__.py
quantinuum_schemas/models/aer_noise.py
quantinuum_schemas/models/backend_config.py
quantinuum_schemas/models/backend_info.py
quantinuum_schemas/models/base.py
quantinuum_schemas/models/emulator_config.py
quantinuum_schemas/models/hypertket_config.py
quantinuum_schemas/models/quantinuum_systems_noise.py
quantinuum_schemas/models/result.py
quantinuum_schemas-7.4.1.dist-info/METADATA
quantinuum_schemas-7.4.1.dist-info/WHEEL
quantinuum_schemas-7.4.1.dist-info/licenses/LICENSE
quantinuum_schemas-7.4.1.dist-info/RECORD
