Metadata-Version: 2.4
Name: quantinuum-schemas
Version: 7.4.1
Summary: Shared data models for Quantinuum.
Project-URL: homepage, https://github.com/CQCL/quantinuum-schemas
Project-URL: repository, https://github.com/CQCL/quantinuum-schemas
Author-email: Matthew Burke <matthew.burke@quantinuum.com>, Quantinuum Nexus Team <QCSupport@quantinuum.com>
License:                                  Apache License
License-File: LICENSE
Requires-Python: <4,>=3.10
Requires-Dist: orjson<4.0.0,>=3.10.18
Requires-Dist: pydantic-extra-types<3.0.0,>=2.10.5
Requires-Dist: pydantic<3,>=2.6.0
